<?xml version="1.0" encoding="UTF-8" standalone="yes"?>
<APIProxy revision="7" name="oidc-v1-google-demo">
    <Basepaths>/azure-b2c</Basepaths>
    <ConfigurationVersion majorVersion="4" minorVersion="0"/>
    <CreatedAt>1583441623621</CreatedAt>
    <CreatedBy>defaultUser</CreatedBy>
    <Description>From oidc-v1-okta-trial, uses GCP project "Edge OIDC Demo"</Description>
    <DisplayName>oidc-v1-google-demo</DisplayName>
    <LastModifiedAt>1583441623621</LastModifiedAt>
    <LastModifiedBy>defaultUser</LastModifiedBy>
    <ManifestVersion>SHA-512:5ff1ba4cdac178332edacd29fd506a19f01c92d91b22f0e7e292d77ce376083e47a88fefd99db4d1b309d3dd23f6f153dd9b6b336624db46e2e19fceb680f856</ManifestVersion>
    <Policies>
        <Policy>AM-AddCORS</Policy>
        <Policy>AM-AuthSession</Policy>
        <Policy>AM-Debug</Policy>
        <Policy>AM-RedirectAppCallback</Policy>
        <Policy>AM-RedirectAppCallbackError</Policy>
        <Policy>AM-RedirectAppCallbackImplicit</Policy>
        <Policy>AM-RedirectLoginApplicationCode</Policy>
        <Policy>AM-RedirectLoginApplicationImplicit</Policy>
        <Policy>AM-SaveRequest</Policy>
        <Policy>AM-SetRequest</Policy>
        <Policy>AM-SetResponseType</Policy>
        <Policy>AM-SetTokenCodeRequest</Policy>
        <Policy>AM-SetTokenCodeResponse</Policy>
        <Policy>AM-SetTokenImplicitRequest</Policy>
        <Policy>AM-SetTokenRefreshRequest</Policy>
        <Policy>AM-SetTokenRefreshResponse</Policy>
        <Policy>AM-SetTokenRevokeRequest</Policy>
        <Policy>AM-SetUserinfoRequest</Policy>
        <Policy>AM-TargetURL</Policy>
        <Policy>DJ-IDToken</Policy>
        <Policy>EV-AuthSession</Policy>
        <Policy>EV-AuthorizeParams</Policy>
        <Policy>EV-CallbackParams</Policy>
        <Policy>EV-GetExternalTokenValues</Policy>
        <Policy>JS-CalculateExpiresIn</Policy>
        <Policy>JS-SetUserinfoResponse</Policy>
        <Policy>KV-Params</Policy>
        <Policy>LC-Session</Policy>
        <Policy>OA-GenerateAccessTokenCode</Policy>
        <Policy>OA-GenerateAccessTokenImplicit</Policy>
        <Policy>OA-GenerateAccessTokenRefresh</Policy>
        <Policy>OA-GenerateAuthCode</Policy>
        <Policy>OA-GetAuthCodeAttributes</Policy>
        <Policy>OA-GetRefreshTokenAttributes</Policy>
        <Policy>OA-RevokeAccessToken</Policy>
        <Policy>OA-VerifyAccessToken</Policy>
        <Policy>OA-VerifyAccessTokenParam</Policy>
        <Policy>PC-Session</Policy>
        <Policy>RF-NoCode</Policy>
        <Policy>RF-NoRefresh</Policy>
        <Policy>RF-NotFound</Policy>
        <Policy>VA-FormParam</Policy>
        <Policy>VA-QueryParam</Policy>
    </Policies>
    <ProxyEndpoints>
        <ProxyEndpoint>default</ProxyEndpoint>
    </ProxyEndpoints>
    <Resources>
        <Resource>jsc://JS-CalculateExpiresIn.js</Resource>
        <Resource>jsc://JS-SetUserinfoResponse.js</Resource>
    </Resources>
    <Spec></Spec>
    <TargetServers/>
    <TargetEndpoints>
        <TargetEndpoint>default</TargetEndpoint>
    </TargetEndpoints>
</APIProxy>
